{"heading":90,"x":86,"y":289,"size":2,"rotationStyle":"normal","physicsMode":"static","triggerLayer":1,"triggerMask":1,"collisionLayer":1,"collisionMask":1,"gravity":0,"costumeIndex":0,"visible":false,"isDraggable":false,"collisionPivot":{"x":-0.0817843866171053,"y":5.506815365551425},"collisionShapeType":"rect","collisionShapeParams":[6.5,11],"costumes":[{"x":6.663568773234211,"y":22.01363073110285,"faceRight":0,"bitmapResolution":2,"name":"书桌","path":"书桌.png","builder_id":"yOdwtmWzHCnbtAb60Klfe"}],"fAnimations":{},"animBindings":{},"builder_id":"9rlJcWG06Zqtofe86gROo"}